runch/__init__.py
runch/__main__.py
runch/_reader.py
runch/_type_utils.py
runch/exceptions.py
runch/py.typed
runch/runch.py
runch/script/__init__.py
runch/script/custom_formatter.py
runch/script/schema_generator.py
runch/script/test.py
runch/test/__main__.py
runch/test/test.yaml
runch/test/test_async_cached.py
runch/test/test_async_logger.py
runch/test/test_async_reader.py
runch/test/test_lax.yaml
runch/test/test_logger.py
runch/test/test_py_ops.py
runch/test/test_reader.py
runch/test/test_strict.yaml
runch-1.10.0.dist-info/LICENSE
runch-1.10.0.dist-info/METADATA
runch-1.10.0.dist-info/WHEEL
runch-1.10.0.dist-info/RECORD
