Metadata-Version: 2.3
Name: runch
Version: 1.10.0
Summary: Runch: refined munch. Attribute-style access for python dicts, with generic typing support. Help handle your configs, data, and more.
License: Apache-2.0
Author: XieJiSS
Author-email: panrz@deepseek.com
Requires-Python: >=3.12,<4.0
Classifier: License :: OSI Approved :: Apache Software License
Classifier: Programming Language :: Python :: 3
Classifier: Programming Language :: Python :: 3.12
Classifier: Programming Language :: Python :: 3.13
Requires-Dist: datamodel-code-generator (>=0.27.3,<0.28.0)
Requires-Dist: pydantic (>=2.9.2,<3.0.0)
Requires-Dist: runch-mergedeep (>=1.3.5,<2.0.0)
Project-URL: Repository, https://github.com/XieJiSS/runch.git
